[[{"isTitle": true, "value": "34a 12.11.70 Queenstown [ZK-DBV Britten-Norman BN 2A Islander]"}, {"label": "View item details", "isLink": true, "value": "https://collection.motat.nz/objects/108088"}, {"isImage": true, "value": "https://collection.motat.nz/records/images/large/3226/a4583ab660f0152183f9853b76a47b1c21bf7dad.jpg"}, {"label": "Year acquired", "value": "1970-11-12Z"}, {"label": "Country of origin", "value": "New Zealand"}], [{"isTitle": true, "value": "33a 12.11.70 Queenstown [ZK-DBV Britten-Norman BN 2A Islander]"}, {"label": "View item details", "isLink": true, "value": "https://collection.motat.nz/objects/108089"}, {"isImage": true, "value": "https://collection.motat.nz/records/images/large/3227/2cba3166c3b731c7aa0519819f4d78e5afe4a0f1.jpg"}, {"label": "Year acquired", "value": "1970-11-12Z"}, {"label": "Country of origin", "value": "New Zealand"}], [{"isTitle": true, "value": "DBW 17.10.70 Chch [ZK-DBW Britten-Norman BN 2A Islander]"}, {"label": "View item details", "isLink": true, "value": "https://collection.motat.nz/objects/108095"}, {"isImage": true, "value": "https://collection.motat.nz/records/images/large/3233/893b6da490349bc6dc5e253b93b6c073b5763273.jpg"}, {"label": "Year acquired", "value": "1970-10-17Z"}, {"label": "Country of origin", "value": "New Zealand"}], [{"isTitle": true, "value": "29 17.10.70 Christchurch [ZK-DBW Britten-Norman BN 2A Islander]"}, {"label": "View item details", "isLink": true, "value": "https://collection.motat.nz/objects/108096"}, {"isImage": true, "value": "https://collection.motat.nz/records/images/large/3234/14aadf83f566847682b12eba86b0357908772f2a.jpg"}, {"label": "Year acquired", "value": "1970-10-17Z"}, {"label": "Country of origin", "value": "New Zealand"}], [{"isTitle": true, "value": "Timaru 18.9.70 [ZK-DBW Britten-Norman BN 2A Islander]"}, {"label": "View item details", "isLink": true, "value": "https://collection.motat.nz/objects/108097"}, {"isImage": true, "value": "https://collection.motat.nz/records/images/large/3235/aaeebf973f5bc7b2b423f46f346458c7effd2e7d.jpg"}, {"label": "Year acquired", "value": "1970-09-18Z"}, {"label": "Country of origin", "value": "New Zealand"}], [{"isTitle": true, "value": "DBW 18.9.70 Timaru [ZK-DBW Britten-Norman BN 2A Islander]"}, {"label": "View item details", "isLink": true, "value": "https://collection.motat.nz/objects/108098"}, {"isImage": true, "value": "https://collection.motat.nz/records/images/large/3236/d6dfd427d281a783f9f38cf8237f9f5c732091de.jpg"}, {"label": "Year acquired", "value": "1970-09-18Z"}, {"label": "Country of origin", "value": "New Zealand"}], [{"isTitle": true, "value": "ZK-FMS Britten-Norman BN2 Islander 21.9.86 Ardmore"}, {"label": "View item details", "isLink": true, "value": "https://collection.motat.nz/objects/108101"}, {"isImage": true, "value": "https://collection.motat.nz/records/images/large/3240/b397936dc4600c8846791d04eae9d865bdde6f84.jpg"}, {"label": "Year acquired", "value": "1986-09-21Z"}, {"label": "Country of origin", "value": "New Zealand"}], [{"isTitle": true, "value": "ZK-JSB Britten-Norman BN2 Islander 4.6.85 Auckland International Airport"}, {"label": "View item details", "isLink": true, "value": "https://collection.motat.nz/objects/108103"}, {"isImage": true, "value": "https://collection.motat.nz/records/images/large/3242/5968be79626d7814917391bcf69dd8b33f1b6f51.jpg"}, {"label": "Year acquired", "value": "1985-06-04Z"}, {"label": "Country of origin", "value": "New Zealand"}], [{"isTitle": true, "value": "[ZK-JSB Britten-Norman BN2 Islander photograph]"}, {"label": "View item details", "isLink": true, "value": "https://collection.motat.nz/objects/108104"}, {"isImage": true, "value": "https://collection.motat.nz/records/images/large/3243/b9faf3c6e784dc079900d2dfa498871c07730f2c.jpg"}, {"label": "Year acquired", "value": "1985-06-04Z"}, {"label": "Country of origin", "value": "New Zealand"}], [{"isTitle": true, "value": "ZK-JSB Britten-Norman BN2 Islander 8.1.85 Ardmore"}, {"label": "View item details", "isLink": true, "value": "https://collection.motat.nz/objects/108105"}, {"isImage": true, "value": "https://collection.motat.nz/records/images/large/3244/bba36ef5611280585b8e60bcae86c8fe527fc39b.jpg"}, {"label": "Year acquired", "value": "1985-01-08Z"}, {"label": "Country of origin", "value": "New Zealand"}]]