[[{"isTitle": true, "value": "ZK-ETW Cessna 150 29.7.81 Ardmore"}, {"label": "View item details", "isLink": true, "value": "https://collection.motat.nz/objects/109319"}, {"isImage": true, "value": "https://collection.motat.nz/records/images/large/4168/8bdf09c312db404d8a3d6c21326d560105899d24.jpg"}, {"label": "Year acquired", "value": "1981-07-29Z"}, {"label": "Country of origin", "value": "New Zealand"}], [{"isTitle": true, "value": "ZK-ETW Cessna 150 18.10.81 Ardmore"}, {"label": "View item details", "isLink": true, "value": "https://collection.motat.nz/objects/109320"}, {"isImage": true, "value": "https://collection.motat.nz/records/images/large/4169/bb2584e04c090e254f5f05308567d37745064083.jpg"}, {"label": "Year acquired", "value": "1981-10-18Z"}, {"label": "Country of origin", "value": "New Zealand"}], [{"isTitle": true, "value": "ZK-ETW Cessna 152 II Jan 1982 Ardmore"}, {"label": "View item details", "isLink": true, "value": "https://collection.motat.nz/objects/109321"}, {"isImage": true, "value": "https://collection.motat.nz/records/images/large/4170/3230ad4c900a58b1e446bf3485387e8774ecce1d.jpg"}, {"label": "Year acquired", "value": "1982-01-01Z"}, {"label": "Country of origin", "value": "New Zealand"}], [{"isTitle": true, "value": "ZK-ETD Cessna 152 II 1980 Ardmore"}, {"label": "View item details", "isLink": true, "value": "https://collection.motat.nz/objects/109322"}, {"isImage": true, "value": "https://collection.motat.nz/records/images/large/4171/3da0a6be05dedb59ee6b458f5fc79d1704a941ca.jpg"}, {"label": "Year acquired", "value": "1980-01-01Z"}, {"label": "Country of origin", "value": "New Zealand"}], [{"isTitle": true, "value": "ZK-EJW Cessna 152 8.2.79 Ardmore"}, {"label": "View item details", "isLink": true, "value": "https://collection.motat.nz/objects/109323"}, {"isImage": true, "value": "https://collection.motat.nz/records/images/large/4172/0d7e77fe12952cc7ce30f8eee87e9ebf49854c1d.jpg"}, {"label": "Year acquired", "value": "1979-02-08Z"}, {"label": "Country of origin", "value": "New Zealand"}], [{"isTitle": true, "value": "[ZK-EJW Cessna 152 photograph]"}, {"label": "View item details", "isLink": true, "value": "https://collection.motat.nz/objects/109324"}, {"isImage": true, "value": "https://collection.motat.nz/records/images/large/4173/dd08ad6196e2333b491546eecf1e7dd022b7f5b3.jpg"}, {"label": "Year acquired", "value": "1979-02-08Z"}, {"label": "Country of origin", "value": "New Zealand"}], [{"isTitle": true, "value": "ZK-ETZ Cessna 150 29.7.81 Ardmore"}, {"label": "View item details", "isLink": true, "value": "https://collection.motat.nz/objects/109325"}, {"isImage": true, "value": "https://collection.motat.nz/records/images/large/4174/dca3ad93f9dfe1297443b4edddc01f6af24fe53d.jpg"}, {"label": "Year acquired", "value": "1981-07-29Z"}, {"label": "Country of origin", "value": "New Zealand"}], [{"isTitle": true, "value": "ZK-ETZ Cessna 150 18.10.81 Ardmore"}, {"label": "View item details", "isLink": true, "value": "https://collection.motat.nz/objects/109326"}, {"isImage": true, "value": "https://collection.motat.nz/records/images/large/4175/9b34723890c8d93f4d73b1cc62799e92c3e557ff.jpg"}, {"label": "Year acquired", "value": "1981-10-18Z"}, {"label": "Country of origin", "value": "New Zealand"}], [{"isTitle": true, "value": "ZK-ETZ Cessna 152 II Jan 1982 Ardmore"}, {"label": "View item details", "isLink": true, "value": "https://collection.motat.nz/objects/109327"}, {"isImage": true, "value": "https://collection.motat.nz/records/images/large/4176/d14791388eb8e0b58a4daf96d85e2ab19770d1f0.jpg"}, {"label": "Year acquired", "value": "1982-01-01Z"}, {"label": "Country of origin", "value": "New Zealand"}], [{"isTitle": true, "value": "ZK-FCO Cessna 152 II 16.1.94 Ardmore"}, {"label": "View item details", "isLink": true, "value": "https://collection.motat.nz/objects/109328"}, {"isImage": true, "value": "https://collection.motat.nz/records/images/large/4177/d59d130bb8adae190b3b70fcdabc70db6b1a168d.jpg"}, {"label": "Year acquired", "value": "1994-01-16Z"}, {"label": "Country of origin", "value": "New Zealand"}]]