[[{"isTitle": true, "value": "Photograph of Princess Elizabeth signing a book at Short Brothers and Harland's factory in Belfast"}, {"label": "View item details", "isLink": true, "value": "https://collection.motat.nz/objects/1120"}, {"isImage": true, "value": "https://collection.motat.nz/records/images/large/6455/acc8ab2d84331ea4987fac1ad2c4fa0703b2855c.jpg"}, {"label": "Year acquired", "value": "1949-01-01Z"}, {"label": "Country of origin", "value": "New Zealand"}], [{"isTitle": true, "value": "[Body of Heron PC80]"}, {"label": "View item details", "isLink": true, "value": "https://collection.motat.nz/objects/112002"}, {"isImage": true, "value": "https://collection.motat.nz/records/images/large/49456/a215e4ae65a38c25753a23e2909facd63416bada.jpg"}, {"label": "Year acquired", "value": "1995-01-01Z"}, {"label": "Country of origin", "value": "New Zealand"}], [{"isTitle": true, "value": "[Body unpainted Heron PC80 outside]"}, {"label": "View item details", "isLink": true, "value": "https://collection.motat.nz/objects/112003"}, {"isImage": true, "value": "https://collection.motat.nz/records/images/large/49457/c4d8e8a5a42499683c995daa6db59fdce2a8aa5f.jpg"}, {"label": "Year acquired", "value": "1995-01-01Z"}, {"label": "Country of origin", "value": "New Zealand"}], [{"isTitle": true, "value": "[Gluing Heron PC80 body together]"}, {"label": "View item details", "isLink": true, "value": "https://collection.motat.nz/objects/112005"}, {"isImage": true, "value": "https://collection.motat.nz/records/images/large/49459/02aa15fc92ee6c4cfa48e6870a65aaa2e5716c5e.jpg"}, {"label": "Year acquired", "value": "1995-01-01Z"}, {"label": "Country of origin", "value": "New Zealand"}], [{"isTitle": true, "value": "[Unidentified man seated in body of Heron PC80 during construction]"}, {"label": "View item details", "isLink": true, "value": "https://collection.motat.nz/objects/112007"}, {"isImage": true, "value": "https://collection.motat.nz/records/images/large/49461/ac6fb7ee952ca1df8e8def2182c931e9ffb855fa.jpg"}, {"label": "Year acquired", "value": "1995-01-01Z"}, {"label": "Country of origin", "value": "New Zealand"}], [{"isTitle": true, "value": "[Close up of front subframe to hold batteries and suspension of Heron PC80]"}, {"label": "View item details", "isLink": true, "value": "https://collection.motat.nz/objects/112008"}, {"isImage": true, "value": "https://collection.motat.nz/records/images/large/49462/38ab1fffca47a534bf6faaa9eaae1b19e9553df1.jpg"}, {"label": "Year acquired", "value": "1995-01-01Z"}, {"label": "Country of origin", "value": "New Zealand"}], [{"isTitle": true, "value": "[Front subframe to hold batteries and suspension on Heron PC80]"}, {"label": "View item details", "isLink": true, "value": "https://collection.motat.nz/objects/112009"}, {"isImage": true, "value": "https://collection.motat.nz/records/images/large/49463/7dbca9b152b5b146b0da0463b30f36f0e7ebce50.jpg"}, {"label": "Year acquired", "value": "1995-01-01Z"}, {"label": "Country of origin", "value": "New Zealand"}], [{"isTitle": true, "value": "[Component of chassis for heron PC80]"}, {"label": "View item details", "isLink": true, "value": "https://collection.motat.nz/objects/112011"}, {"isImage": true, "value": "https://collection.motat.nz/records/images/large/49465/af890c65e735cf3ba7b23eacec9a622cadfb403c.jpg"}, {"label": "Year acquired", "value": "1995-01-01Z"}, {"label": "Country of origin", "value": "New Zealand"}], [{"isTitle": true, "value": "[Chassis on Heron PC80]"}, {"label": "View item details", "isLink": true, "value": "https://collection.motat.nz/objects/112012"}, {"isImage": true, "value": "https://collection.motat.nz/records/images/large/49466/9c85d6d0b5025803f9a2b1d87df15b2c87650147.jpg"}, {"label": "Year acquired", "value": "1995-01-01Z"}, {"label": "Country of origin", "value": "New Zealand"}], [{"isTitle": true, "value": "[Rear subframe to hold battery suspension on Heron PC80]"}, {"label": "View item details", "isLink": true, "value": "https://collection.motat.nz/objects/112013"}, {"isImage": true, "value": "https://collection.motat.nz/records/images/large/49467/0b212f5df194ccff96a694e72eee59efb1d180f5.jpg"}, {"label": "Year acquired", "value": "1995-01-01Z"}, {"label": "Country of origin", "value": "New Zealand"}]]