[[{"isTitle": true, "value": "[Quotation for a Wolesley Milking Machine]"}, {"label": "View item details", "isLink": true, "value": "https://collection.motat.nz/objects/106580"}, {"isImage": true, "value": "https://collection.motat.nz/records/images/large/1614/e50ecd3356d1b00de6f8b1c89546654aacaf379e.jpg"}, {"label": "Year acquired", "value": "1917-01-01Z"}, {"label": "Country of origin", "value": "New Zealand"}], [{"isTitle": true, "value": "[Air New Zealand DC-8 inaugural flight covers]"}, {"label": "View item details", "isLink": true, "value": "https://collection.motat.nz/objects/106586"}, {"isImage": true, "value": "https://collection.motat.nz/records/images/large/1615/520ad787c335d2e240a4a4ea4e03bc31b3885f47.jpg"}, {"label": "Year acquired", "value": "1965-01-01Z"}, {"label": "Country of origin", "value": "New Zealand"}], [{"isTitle": true, "value": "Medal [Commemorative City of Auckland Centennial Medal in Presentation Box]"}, {"label": "View item details", "isLink": true, "value": "https://collection.motat.nz/objects/10659"}, {"isImage": true, "value": "https://collection.motat.nz/records/images/large/1619/51080fd8d510af652abb0222d517d867830c8030.jpg"}, {"label": "Year acquired", "value": "1971-01-01Z"}, {"label": "Country of origin", "value": "New Zealand"}], [{"isTitle": true, "value": "Floppy Disk [Commodore 64 Game: Laser Tag]"}, {"label": "View item details", "isLink": true, "value": "https://collection.motat.nz/objects/106605"}, {"isImage": true, "value": "https://collection.motat.nz/records/images/large/1636/cc5425aa50033d2994ef6b71b9c6f10769a15619.jpg"}, {"label": "Year acquired", "value": "1987-01-01Z"}, {"label": "Country of origin", "value": "New Zealand"}], [{"isTitle": true, "value": "Commemorative Medal for Richard Pearse in Presentation Casing"}, {"label": "View item details", "isLink": true, "value": "https://collection.motat.nz/objects/10663"}, {"isImage": true, "value": "https://collection.motat.nz/records/images/large/1649/a8d1bfb9b3e072962542b465316b224e6bd58187.jpg"}, {"label": "Year acquired", "value": "1971-01-01Z"}, {"label": "Country of origin", "value": "New Zealand"}], [{"isTitle": true, "value": "Commemorative Medal for Richard Pearse in Presentation box"}, {"label": "View item details", "isLink": true, "value": "https://collection.motat.nz/objects/10664"}, {"isImage": true, "value": "https://collection.motat.nz/records/images/large/1660/140f66da2441010942d1fed9da8c1fda3f91e670.jpg"}, {"label": "Year acquired", "value": "1971-01-01Z"}, {"label": "Country of origin", "value": "New Zealand"}], [{"isTitle": true, "value": "ZK-CTU Aero Commander 100 5.6.83 Ardmore"}, {"label": "View item details", "isLink": true, "value": "https://collection.motat.nz/objects/106696"}, {"isImage": true, "value": "https://collection.motat.nz/records/images/large/1702/386ad7923a8b15182745a963e5534b0b36af06ed.jpg"}, {"label": "Year acquired", "value": "1983-06-05Z"}, {"label": "Country of origin", "value": "New Zealand"}], [{"isTitle": true, "value": "16.10.71 Ardmore [ZK-CTU Aero Commander 100]"}, {"label": "View item details", "isLink": true, "value": "https://collection.motat.nz/objects/106698"}, {"isImage": true, "value": "https://collection.motat.nz/records/images/large/1704/da8f27c6b2d123ae11ac46ef6d8b89943d0d4ae4.jpg"}, {"label": "Year acquired", "value": "1971-10-16Z"}, {"label": "Country of origin", "value": "New Zealand"}], [{"isTitle": true, "value": "[ZK-CTU Aero Commander 100 negative 10]"}, {"label": "View item details", "isLink": true, "value": "https://collection.motat.nz/objects/106703"}, {"isImage": true, "value": "https://collection.motat.nz/records/images/large/1709/52a58acf86d52fec87b9222c93771c7dc56f8dee.jpg"}, {"label": "Year acquired", "value": "1969-01-04Z"}, {"label": "Country of origin", "value": "New Zealand"}], [{"isTitle": true, "value": "[ZK-CTU Aero Commander 100 negative 11]"}, {"label": "View item details", "isLink": true, "value": "https://collection.motat.nz/objects/106704"}, {"isImage": true, "value": "https://collection.motat.nz/records/images/large/1710/bdb876d0d568e770a09ab46654af6089dca1cf59.jpg"}, {"label": "Year acquired", "value": "1969-01-04Z"}, {"label": "Country of origin", "value": "New Zealand"}]]