[[{"isTitle": true, "value": "Otahuhu Volunteer Fire Brigade 1929"}, {"label": "View item details", "isLink": true, "value": "https://collection.motat.nz/objects/48889"}, {"isImage": true, "value": "https://collection.motat.nz/records/images/large/21156/adb7478d7f943e1a5fd8e6b533b4b8f6bfeaa688.jpg"}, {"label": "Year acquired", "value": "1929-01-01Z"}, {"label": "Country of origin", "value": "New Zealand"}], [{"isTitle": true, "value": "[1953 -1954 Royal Tour of Queen Elizabeth II and the Duke of Edinburgh]"}, {"label": "View item details", "isLink": true, "value": "https://collection.motat.nz/objects/48907"}, {"isImage": true, "value": "https://collection.motat.nz/records/images/large/21157/0e0033ac9ceef7d9a095af5140c241d8219d83c7.jpg"}, {"label": "Year acquired", "value": "1952-01-01Z"}, {"label": "Country of origin", "value": "New Zealand"}], [{"isTitle": true, "value": "[1953 - 1954 Royal Tour of Queen Elizabeth II and the Duke of Edinburgh]"}, {"label": "View item details", "isLink": true, "value": "https://collection.motat.nz/objects/48908"}, {"isImage": true, "value": "https://collection.motat.nz/records/images/large/21158/fc9e9f0b78dbbab5cf455ff7ebab380862242f90.jpg"}, {"label": "Year acquired", "value": "1954-01-17Z"}, {"label": "Country of origin", "value": "New Zealand"}], [{"isTitle": true, "value": "Water under my wings : modern day aviators savour a little of those glorious and heroic years of aviation's infancy"}, {"label": "View item details", "isLink": true, "value": "https://collection.motat.nz/objects/49011"}, {"isImage": true, "value": "https://collection.motat.nz/records/images/large/21163/d7f03a7a1e4d8aba988c177f4dbdf3a0c1bf7078.jpg"}, {"label": "Year acquired", "value": "1980-01-01Z"}, {"label": "Country of origin", "value": "New Zealand"}], [{"isTitle": true, "value": "Long Drop"}, {"label": "View item details", "isLink": true, "value": "https://collection.motat.nz/objects/4906"}, {"isImage": true, "value": "https://collection.motat.nz/records/images/large/21166/51a8b90e40ef7a473f6cd843b1722754d2adfacf.jpg"}, {"label": "Year acquired", "value": "1855-07-02Z"}, {"label": "Country of origin", "value": "New Zealand"}], [{"isTitle": true, "value": "Two children, one older girl and a younger boy, barefoot and laughing in a paddock"}, {"label": "View item details", "isLink": true, "value": "https://collection.motat.nz/objects/49081"}, {"isImage": true, "value": "https://collection.motat.nz/records/images/large/21168/8ce257a093b11939d72d1cd4ad385ab05230034a.jpg"}, {"label": "Year acquired", "value": "1920-01-01Z"}, {"label": "Country of origin", "value": "New Zealand"}], [{"isTitle": true, "value": "Young girl in fairy costume"}, {"label": "View item details", "isLink": true, "value": "https://collection.motat.nz/objects/49092"}, {"isImage": true, "value": "https://collection.motat.nz/records/images/large/21169/9b2a7b38c8c7dae4202c02aaf875c0729a6886b4.jpg"}, {"label": "Year acquired", "value": "1901-01-01Z"}, {"label": "Country of origin", "value": "New Zealand"}], [{"isTitle": true, "value": "Young girl on tricycle in garden"}, {"label": "View item details", "isLink": true, "value": "https://collection.motat.nz/objects/49100"}, {"isImage": true, "value": "https://collection.motat.nz/records/images/large/21170/576b4b5bfd38a63cca5ba03ab539192cd21ebdb3.jpg"}, {"label": "Year acquired", "value": "1920-01-01Z"}, {"label": "Country of origin", "value": "New Zealand"}], [{"isTitle": true, "value": "Woman and black Labrador looking out over harbour"}, {"label": "View item details", "isLink": true, "value": "https://collection.motat.nz/objects/49139"}, {"isImage": true, "value": "https://collection.motat.nz/records/images/large/21171/16932ea15957286c7b7938e92e280bff0f9d4f31.jpg"}, {"label": "Year acquired", "value": "1932-11-02Z"}, {"label": "Country of origin", "value": "New Zealand"}], [{"isTitle": true, "value": "Computer [Apple IIc]"}, {"label": "View item details", "isLink": true, "value": "https://collection.motat.nz/objects/49199"}, {"isImage": true, "value": "https://collection.motat.nz/records/images/large/21172/045c099f6bad9805b8f73d65b0a3df753372238d.jpg"}, {"label": "Year acquired", "value": "1985-01-01Z"}, {"label": "Country of origin", "value": "New Zealand"}]]