[[{"isTitle": true, "value": "Gramophone [Brunswick Panatrope]"}, {"label": "View item details", "isLink": true, "value": "https://collection.motat.nz/objects/5562"}, {"isImage": true, "value": "https://collection.motat.nz/records/images/large/21640/279a5435731b57105d6e56911307c9ba8d10fb38.jpg"}, {"label": "Year acquired", "value": "1915-01-01Z"}, {"label": "Country of origin", "value": "New Zealand"}], [{"isTitle": true, "value": "[Radio log of ham operator for station ZL 2Hi of New Plymouth]"}, {"label": "View item details", "isLink": true, "value": "https://collection.motat.nz/objects/56095"}, {"isImage": true, "value": "https://collection.motat.nz/records/images/large/21651/bb1056c9afae96f31e21e220f31351183ad8eb00.jpg"}, {"label": "Year acquired", "value": "1923-01-01Z"}, {"label": "Country of origin", "value": "New Zealand"}], [{"isTitle": true, "value": "[Letter relating to the death of radio operators on Tarawa Island during WWII]"}, {"label": "View item details", "isLink": true, "value": "https://collection.motat.nz/objects/56098"}, {"isImage": true, "value": "https://collection.motat.nz/records/images/large/21654/364b3ae64f4ba119ad371e3caf64aca35115c88d.jpg"}, {"label": "Year acquired", "value": "1944-10-25Z"}, {"label": "Country of origin", "value": "New Zealand"}], [{"isTitle": true, "value": "[Certificate to ham operator Les Birch of station ZL 2Hi New Plymouth]"}, {"label": "View item details", "isLink": true, "value": "https://collection.motat.nz/objects/56099"}, {"isImage": true, "value": "https://collection.motat.nz/records/images/large/21656/d960e2f025830eef4d2888747e7eb7298b8016d7.jpg"}, {"label": "Year acquired", "value": "1931-10-15Z"}, {"label": "Country of origin", "value": "New Zealand"}], [{"isTitle": true, "value": "[Dinner for Air Commodore Sir Charles Kingsford Smith]"}, {"label": "View item details", "isLink": true, "value": "https://collection.motat.nz/objects/56101"}, {"isImage": true, "value": "https://collection.motat.nz/records/images/large/21657/7808ff3a0dc5343c921e79a0785d200166307e9c.jpg"}, {"label": "Year acquired", "value": "1933-01-01Z"}, {"label": "Country of origin", "value": "New Zealand"}], [{"isTitle": true, "value": "[Menu for dinner commemorating Tasman flight on \"Faith in Australia\"]"}, {"label": "View item details", "isLink": true, "value": "https://collection.motat.nz/objects/56102"}, {"isImage": true, "value": "https://collection.motat.nz/records/images/large/21658/f8033ae21206b6e5e7c88f3798660977b3d20829.jpg"}, {"label": "Year acquired", "value": "1933-01-01Z"}, {"label": "Country of origin", "value": "New Zealand"}], [{"isTitle": true, "value": "[Menu for a dinner held for Sir Charles Kingsford Smith]"}, {"label": "View item details", "isLink": true, "value": "https://collection.motat.nz/objects/56103"}, {"isImage": true, "value": "https://collection.motat.nz/records/images/large/21660/39d638e72ee108159df9ae983c1a25719ba20fbd.jpg"}, {"label": "Year acquired", "value": "1933-01-12Z"}, {"label": "Country of origin", "value": "New Zealand"}], [{"isTitle": true, "value": "[Letter from Auckland School of Wireless and Radio to Les Birch]"}, {"label": "View item details", "isLink": true, "value": "https://collection.motat.nz/objects/56104"}, {"isImage": true, "value": "https://collection.motat.nz/records/images/large/21663/2d6368dca03e9e2817706269ebf60457b7bbd701.jpg"}, {"label": "Year acquired", "value": "1936-04-18Z"}, {"label": "Country of origin", "value": "New Zealand"}], [{"isTitle": true, "value": "[Thanking Les Birch for radio communication with \"Southern Cross\" in flight]"}, {"label": "View item details", "isLink": true, "value": "https://collection.motat.nz/objects/56105"}, {"isImage": true, "value": "https://collection.motat.nz/records/images/large/21664/75b4e1d3b015946cb901cf814dd051264d8cc89a.jpg"}, {"label": "Year acquired", "value": "1933-01-27Z"}, {"label": "Country of origin", "value": "New Zealand"}], [{"isTitle": true, "value": "License to establish and operate a radio receiving-station [for Les Birch]"}, {"label": "View item details", "isLink": true, "value": "https://collection.motat.nz/objects/56106"}, {"isImage": true, "value": "https://collection.motat.nz/records/images/large/21665/59fbab433bddaf5803e56e8d78fb0358e7e1da75.jpg"}, {"label": "Year acquired", "value": "1926-05-07Z"}, {"label": "Country of origin", "value": "New Zealand"}]]