[[{"isTitle": true, "value": "Photograph of Hudswell diesel shunter T 54"}, {"label": "View item details", "isLink": true, "value": "https://collection.motat.nz/objects/86804"}, {"isImage": true, "value": "https://collection.motat.nz/records/images/large/37860/273737cc9ab7e2a2916c9c4838c8a73d77645006.jpg"}, {"label": "Year acquired", "value": "1972-01-01Z"}, {"label": "Country of origin", "value": "New Zealand"}], [{"isTitle": true, "value": "Photograph of rail crane 291"}, {"label": "View item details", "isLink": true, "value": "https://collection.motat.nz/objects/86805"}, {"isImage": true, "value": "https://collection.motat.nz/records/images/large/37861/b59a2ad295e95252fe335efa891892c5905693f5.jpg"}, {"label": "Year acquired", "value": "1972-01-01Z"}, {"label": "Country of origin", "value": "New Zealand"}], [{"isTitle": true, "value": "Photograph of steel wagon RP 5004"}, {"label": "View item details", "isLink": true, "value": "https://collection.motat.nz/objects/86810"}, {"isImage": true, "value": "https://collection.motat.nz/records/images/large/37866/ad1c9dec74f076212791ad8bd2621c819e0a3a2e.jpg"}, {"label": "Year acquired", "value": "1972-01-01Z"}, {"label": "Country of origin", "value": "New Zealand"}], [{"isTitle": true, "value": "Photograph of freight van"}, {"label": "View item details", "isLink": true, "value": "https://collection.motat.nz/objects/86813"}, {"isImage": true, "value": "https://collection.motat.nz/records/images/large/37869/248d8e79dbc6f00aade3c86e0eb0773f2d9db808.jpg"}, {"label": "Year acquired", "value": "1972-01-01Z"}, {"label": "Country of origin", "value": "New Zealand"}], [{"isTitle": true, "value": "Photograph of large rail crane"}, {"label": "View item details", "isLink": true, "value": "https://collection.motat.nz/objects/86814"}, {"isImage": true, "value": "https://collection.motat.nz/records/images/large/37870/196070c3a07bbea611a69aa8dc9ed7dd7d85bec7.jpg"}, {"label": "Year acquired", "value": "1972-01-01Z"}, {"label": "Country of origin", "value": "New Zealand"}], [{"isTitle": true, "value": "Photograph of sheep wagon H 976"}, {"label": "View item details", "isLink": true, "value": "https://collection.motat.nz/objects/86815"}, {"isImage": true, "value": "https://collection.motat.nz/records/images/large/37871/6e9f0d3360ce479c4edc4421632da2dc5c3d8346.jpg"}, {"label": "Year acquired", "value": "1972-01-01Z"}, {"label": "Country of origin", "value": "New Zealand"}], [{"isTitle": true, "value": "Photograph of locomotive DA 1473"}, {"label": "View item details", "isLink": true, "value": "https://collection.motat.nz/objects/86821"}, {"isImage": true, "value": "https://collection.motat.nz/records/images/large/37877/82b93896973c8915b2c29843396e79a229d322c0.jpg"}, {"label": "Year acquired", "value": "1972-01-01Z"}, {"label": "Country of origin", "value": "New Zealand"}], [{"isTitle": true, "value": "Photograph of sleeping car AA 1620"}, {"label": "View item details", "isLink": true, "value": "https://collection.motat.nz/objects/86822"}, {"isImage": true, "value": "https://collection.motat.nz/records/images/large/37878/3bf71b1eab81fda51b13ebef605fd0012976fcef.jpg"}, {"label": "Year acquired", "value": "1972-01-01Z"}, {"label": "Country of origin", "value": "New Zealand"}], [{"isTitle": true, "value": "Photograph of Paeroa railway station"}, {"label": "View item details", "isLink": true, "value": "https://collection.motat.nz/objects/86830"}, {"isImage": true, "value": "https://collection.motat.nz/records/images/large/37886/9be1a8e6ebe261b2e65f84477c448bc56a67ff69.jpg"}, {"label": "Year acquired", "value": "1972-01-01Z"}, {"label": "Country of origin", "value": "New Zealand"}], [{"isTitle": true, "value": "Photograph of Thames Fire Brigade ladder truck"}, {"label": "View item details", "isLink": true, "value": "https://collection.motat.nz/objects/86832"}, {"isImage": true, "value": "https://collection.motat.nz/records/images/large/37888/4d388f600e37582cd8d5051bb781dfd633f2a3d2.jpg"}, {"label": "Year acquired", "value": "1972-01-01Z"}, {"label": "Country of origin", "value": "New Zealand"}]]