[[{"isTitle": true, "value": "Photograph of NZR road depot, Thames"}, {"label": "View item details", "isLink": true, "value": "https://collection.motat.nz/objects/89605"}, {"isImage": true, "value": "https://collection.motat.nz/records/images/large/40583/07c82c5c7a69012935417d287f8814257c92b50c.jpg"}, {"label": "Year acquired", "value": "1985-01-01Z"}, {"label": "Country of origin", "value": "New Zealand"}], [{"isTitle": true, "value": "Photograph of A & G Price workshops, Thames"}, {"label": "View item details", "isLink": true, "value": "https://collection.motat.nz/objects/89606"}, {"isImage": true, "value": "https://collection.motat.nz/records/images/large/40584/33b5308c6de4c9822360cb748ba931fb3451c608.jpg"}, {"label": "Year acquired", "value": "1985-01-01Z"}, {"label": "Country of origin", "value": "New Zealand"}], [{"isTitle": true, "value": "Photograph of Northener carriage detail"}, {"label": "View item details", "isLink": true, "value": "https://collection.motat.nz/objects/89610"}, {"isImage": true, "value": "https://collection.motat.nz/records/images/large/40592/b9b492238707163f34c0d0482006621271bb17d0.jpg"}, {"label": "Year acquired", "value": "1985-01-01Z"}, {"label": "Country of origin", "value": "New Zealand"}], [{"isTitle": true, "value": "Photograph of Intercity carriage A 3022"}, {"label": "View item details", "isLink": true, "value": "https://collection.motat.nz/objects/89613"}, {"isImage": true, "value": "https://collection.motat.nz/records/images/large/40595/19b144497e32f76e7cfc974ca2e0d116857f9cf9.jpg"}, {"label": "Year acquired", "value": "1985-01-01Z"}, {"label": "Country of origin", "value": "New Zealand"}], [{"isTitle": true, "value": "Photograph of bridge over road"}, {"label": "View item details", "isLink": true, "value": "https://collection.motat.nz/objects/89615"}, {"isImage": true, "value": "https://collection.motat.nz/records/images/large/40597/02f22394fd78eac1daf0d1d0eba5039f8d1d74dc.jpg"}, {"label": "Year acquired", "value": "1985-01-01Z"}, {"label": "Country of origin", "value": "New Zealand"}], [{"isTitle": true, "value": "Photograph of ground work at MOTAT"}, {"label": "View item details", "isLink": true, "value": "https://collection.motat.nz/objects/89617"}, {"isImage": true, "value": "https://collection.motat.nz/records/images/large/40599/1414b984a1b994992fd3ecb2df8788ab8385a7fc.jpg"}, {"label": "Year acquired", "value": "1985-01-01Z"}, {"label": "Country of origin", "value": "New Zealand"}], [{"isTitle": true, "value": "Photograph of locomotive DB 1145"}, {"label": "View item details", "isLink": true, "value": "https://collection.motat.nz/objects/89618"}, {"isImage": true, "value": "https://collection.motat.nz/records/images/large/40600/a93d6c8976645955e46b588dd55abe410256df90.jpg"}, {"label": "Year acquired", "value": "1985-01-01Z"}, {"label": "Country of origin", "value": "New Zealand"}], [{"isTitle": true, "value": "Photograph of council offices, Coromandel"}, {"label": "View item details", "isLink": true, "value": "https://collection.motat.nz/objects/89621"}, {"isImage": true, "value": "https://collection.motat.nz/records/images/large/40603/8daac4991389ee876e8e241ff70618f3f72314ea.jpg"}, {"label": "Year acquired", "value": "1985-01-01Z"}, {"label": "Country of origin", "value": "New Zealand"}], [{"isTitle": true, "value": "Photograph of bridge over creek"}, {"label": "View item details", "isLink": true, "value": "https://collection.motat.nz/objects/89622"}, {"isImage": true, "value": "https://collection.motat.nz/records/images/large/40604/b5c8443360ba398b31c61744b839063b58d84e24.jpg"}, {"label": "Year acquired", "value": "1985-01-01Z"}, {"label": "Country of origin", "value": "New Zealand"}], [{"isTitle": true, "value": "Photograph of scow"}, {"label": "View item details", "isLink": true, "value": "https://collection.motat.nz/objects/89623"}, {"isImage": true, "value": "https://collection.motat.nz/records/images/large/40605/a87ddc8acb404b47bb5ddf23c7214a8f64ae02f6.jpg"}, {"label": "Year acquired", "value": "1985-01-01Z"}, {"label": "Country of origin", "value": "New Zealand"}]]