[[{"isTitle": true, "value": "Family portrait in front of wooden garden trellis"}, {"label": "View item details", "isLink": true, "value": "https://collection.motat.nz/objects/89811"}, {"isImage": true, "value": "https://collection.motat.nz/records/images/large/40765/cbb06c754e5dc2f5151fa3e10a1cae35318fad44.jpg"}, {"label": "Year acquired", "value": "1930-01-01Z"}, {"label": "Country of origin", "value": "New Zealand"}], [{"isTitle": true, "value": "Family portrait in living room"}, {"label": "View item details", "isLink": true, "value": "https://collection.motat.nz/objects/89812"}, {"isImage": true, "value": "https://collection.motat.nz/records/images/large/40766/c1dcf1c155c1f63db61097fd3bc989618a2a1210.jpg"}, {"label": "Year acquired", "value": "1930-01-01Z"}, {"label": "Country of origin", "value": "New Zealand"}], [{"isTitle": true, "value": "John George McGuire's backyard shed"}, {"label": "View item details", "isLink": true, "value": "https://collection.motat.nz/objects/89813"}, {"isImage": true, "value": "https://collection.motat.nz/records/images/large/40767/fbd9dccf78e10ab1a16becf3bbad3411346f3067.jpg"}, {"label": "Year acquired", "value": "1935-01-01Z"}, {"label": "Country of origin", "value": "New Zealand"}], [{"isTitle": true, "value": "Boating accident and rescue"}, {"label": "View item details", "isLink": true, "value": "https://collection.motat.nz/objects/89814"}, {"isImage": true, "value": "https://collection.motat.nz/records/images/large/40768/50f6fe9e3536a9428fd2a5d41512c71df94a4f92.jpg"}, {"label": "Year acquired", "value": "1928-01-01Z"}, {"label": "Country of origin", "value": "New Zealand"}], [{"isTitle": true, "value": "Group portrait at evening function"}, {"label": "View item details", "isLink": true, "value": "https://collection.motat.nz/objects/89815"}, {"isImage": true, "value": "https://collection.motat.nz/records/images/large/40769/ee97450b3d4a2319da8444e4e2099896f2731f2a.jpg"}, {"label": "Year acquired", "value": "1930-01-01Z"}, {"label": "Country of origin", "value": "New Zealand"}], [{"isTitle": true, "value": "Girl standing on garden path"}, {"label": "View item details", "isLink": true, "value": "https://collection.motat.nz/objects/89818"}, {"isImage": true, "value": "https://collection.motat.nz/records/images/large/40772/7703ae92894193742a44075254be41bc504f8615.jpg"}, {"label": "Year acquired", "value": "1930-01-01Z"}, {"label": "Country of origin", "value": "New Zealand"}], [{"isTitle": true, "value": "Group portrait"}, {"label": "View item details", "isLink": true, "value": "https://collection.motat.nz/objects/89821"}, {"isImage": true, "value": "https://collection.motat.nz/records/images/large/40775/c747dda37c2ea398966948fcfeba435bd098080a.jpg"}, {"label": "Year acquired", "value": "1930-01-01Z"}, {"label": "Country of origin", "value": "New Zealand"}], [{"isTitle": true, "value": "Spiral staircase"}, {"label": "View item details", "isLink": true, "value": "https://collection.motat.nz/objects/89822"}, {"isImage": true, "value": "https://collection.motat.nz/records/images/large/40776/fc0b150cb245efce3db6d64e8539a3098a76894d.jpg"}, {"label": "Year acquired", "value": "1930-01-01Z"}, {"label": "Country of origin", "value": "New Zealand"}], [{"isTitle": true, "value": "Man standing in garden"}, {"label": "View item details", "isLink": true, "value": "https://collection.motat.nz/objects/89824"}, {"isImage": true, "value": "https://collection.motat.nz/records/images/large/40778/561778b11852558af94ea0e3886faecf28977d53.jpg"}, {"label": "Year acquired", "value": "1930-01-01Z"}, {"label": "Country of origin", "value": "New Zealand"}], [{"isTitle": true, "value": "Woman standing in garden"}, {"label": "View item details", "isLink": true, "value": "https://collection.motat.nz/objects/89825"}, {"isImage": true, "value": "https://collection.motat.nz/records/images/large/40779/d52071344f34f54ce51a4da344c7537ef0064430.jpg"}, {"label": "Year acquired", "value": "1930-01-01Z"}, {"label": "Country of origin", "value": "New Zealand"}]]