[[{"isTitle": true, "value": "Evening function in full swing in hall"}, {"label": "View item details", "isLink": true, "value": "https://collection.motat.nz/objects/89865"}, {"isImage": true, "value": "https://collection.motat.nz/records/images/large/40822/ba6f23b4a452b4ca40df6cad7064cd37becede65.jpg"}, {"label": "Year acquired", "value": "1930-01-01Z"}, {"label": "Country of origin", "value": "New Zealand"}], [{"isTitle": true, "value": "Akarana Yacht Club"}, {"label": "View item details", "isLink": true, "value": "https://collection.motat.nz/objects/89866"}, {"isImage": true, "value": "https://collection.motat.nz/records/images/large/40823/4a9fe6fe9ad1744d4aa34e3a2f71c3a8b1ee45e3.jpg"}, {"label": "Year acquired", "value": "1934-01-01Z"}, {"label": "Country of origin", "value": "New Zealand"}], [{"isTitle": true, "value": "1929 Erskine car"}, {"label": "View item details", "isLink": true, "value": "https://collection.motat.nz/objects/89867"}, {"isImage": true, "value": "https://collection.motat.nz/records/images/large/40824/d381620833e2c2d221f077be98d18415e0443077.jpg"}, {"label": "Year acquired", "value": "1930-01-01Z"}, {"label": "Country of origin", "value": "New Zealand"}], [{"isTitle": true, "value": "Woman in renaissance costume with riding crop"}, {"label": "View item details", "isLink": true, "value": "https://collection.motat.nz/objects/89868"}, {"isImage": true, "value": "https://collection.motat.nz/records/images/large/40825/6fc608463bc55adc5d9772c2d19d14e3b76c6db8.jpg"}, {"label": "Year acquired", "value": "1930-01-01Z"}, {"label": "Country of origin", "value": "New Zealand"}], [{"isTitle": true, "value": "Workplace"}, {"label": "View item details", "isLink": true, "value": "https://collection.motat.nz/objects/89869"}, {"isImage": true, "value": "https://collection.motat.nz/records/images/large/40826/aaecb9afdee2bb6f2ba2ece37907a7a52f18dd1c.jpg"}, {"label": "Year acquired", "value": "1930-01-01Z"}, {"label": "Country of origin", "value": "New Zealand"}], [{"isTitle": true, "value": "Men seated at event"}, {"label": "View item details", "isLink": true, "value": "https://collection.motat.nz/objects/89870"}, {"isImage": true, "value": "https://collection.motat.nz/records/images/large/40827/d4d3277ac03397a442f145c504ac3244a5e60e96.jpg"}, {"label": "Year acquired", "value": "1930-01-01Z"}, {"label": "Country of origin", "value": "New Zealand"}], [{"isTitle": true, "value": "Advertising display for travelling circus created in retail entrance"}, {"label": "View item details", "isLink": true, "value": "https://collection.motat.nz/objects/89871"}, {"isImage": true, "value": "https://collection.motat.nz/records/images/large/40828/8110aad496eabe5b763e9c098908220103bc3c6b.jpg"}, {"label": "Year acquired", "value": "1930-01-01Z"}, {"label": "Country of origin", "value": "New Zealand"}], [{"isTitle": true, "value": "Group portrait of men seated in theatre"}, {"label": "View item details", "isLink": true, "value": "https://collection.motat.nz/objects/89874"}, {"isImage": true, "value": "https://collection.motat.nz/records/images/large/40831/da3a9650e7fd79625d38e3e00451d74e33c596d3.jpg"}, {"label": "Year acquired", "value": "1930-01-01Z"}, {"label": "Country of origin", "value": "New Zealand"}], [{"isTitle": true, "value": "Group portrait in small hall"}, {"label": "View item details", "isLink": true, "value": "https://collection.motat.nz/objects/89876"}, {"isImage": true, "value": "https://collection.motat.nz/records/images/large/40833/a1dd4021b2eceff754e0c47843a2085a77d584d0.jpg"}, {"label": "Year acquired", "value": "1930-01-01Z"}, {"label": "Country of origin", "value": "New Zealand"}], [{"isTitle": true, "value": "Victoria Cruising Club and Akarana Yacht Club"}, {"label": "View item details", "isLink": true, "value": "https://collection.motat.nz/objects/89878"}, {"isImage": true, "value": "https://collection.motat.nz/records/images/large/40835/d223e984a957fd8b7b99e7448467ebfa8f346644.jpg"}, {"label": "Year acquired", "value": "1934-01-01Z"}, {"label": "Country of origin", "value": "New Zealand"}]]