[[{"isTitle": true, "value": "Bicycle [Bambike]"}, {"label": "View item details", "isLink": true, "value": "https://collection.motat.nz/objects/91131"}, {"isImage": true, "value": "https://collection.motat.nz/records/images/large/50320/0be5c1d0965e7246b1e306f3e9be856c37f2c26e.jpg"}, {"label": "Year acquired", "value": "2012-01-01Z"}, {"label": "Country of origin", "value": "New Zealand"}], [{"isTitle": true, "value": "Guns against tanks L Troop, 33rd Battery, 7th New Zealand Anti-Tank Regiment in Libya, 23 November 1941"}, {"label": "View item details", "isLink": true, "value": "https://collection.motat.nz/objects/91164"}, {"isImage": true, "value": "https://collection.motat.nz/records/images/large/41573/314a5f01c89fb7a2219c388414fa7ac1c79a846a.jpg"}, {"label": "Year acquired", "value": "1948-01-01Z"}, {"label": "Country of origin", "value": "New Zealand"}], [{"isTitle": true, "value": "Bracelet and Medal [Mourning Bracelet]"}, {"label": "View item details", "isLink": true, "value": "https://collection.motat.nz/objects/91202"}, {"isImage": true, "value": "https://collection.motat.nz/records/images/large/41584/c6212a15fbb867e31979e87adf7156b1a2f91f11.jpg"}, {"label": "Year acquired", "value": "1914-01-01Z"}, {"label": "Country of origin", "value": "New Zealand"}], [{"isTitle": true, "value": "Distograph [MacMillan's]"}, {"label": "View item details", "isLink": true, "value": "https://collection.motat.nz/objects/91216"}, {"isImage": true, "value": "https://collection.motat.nz/records/images/large/41589/5e7aa4808173c336493b5f099566f4e94001cc81.jpg"}, {"label": "Year acquired", "value": "1918-01-01Z"}, {"label": "Country of origin", "value": "New Zealand"}], [{"isTitle": true, "value": "Record [Vinyl] \"Songs of the South Seas\""}, {"label": "View item details", "isLink": true, "value": "https://collection.motat.nz/objects/91232"}, {"isImage": true, "value": "https://collection.motat.nz/records/images/large/41597/1f96ba8e0569a21bfe8f8683ea0851b28ceaedfd.jpg"}, {"label": "Year acquired", "value": "1961-01-01Z"}, {"label": "Country of origin", "value": "New Zealand"}], [{"isTitle": true, "value": "Record [Vinyl] \"Our South Pacific\""}, {"label": "View item details", "isLink": true, "value": "https://collection.motat.nz/objects/91245"}, {"isImage": true, "value": "https://collection.motat.nz/records/images/large/41602/0bf5c5f317763ae54282fe4bcd6aec10cb4c2349.jpg"}, {"label": "Year acquired", "value": "1972-01-01Z"}, {"label": "Country of origin", "value": "New Zealand"}], [{"isTitle": true, "value": "Installation & maintenance of electrical machines transformers, rectifiers, capacitors and associated equipment"}, {"label": "View item details", "isLink": true, "value": "https://collection.motat.nz/objects/91310"}, {"isImage": true, "value": "https://collection.motat.nz/records/images/large/41610/9fb802c4b9b96de6c926393e7846658567168756.jpg"}, {"label": "Year acquired", "value": "1950-01-01Z"}, {"label": "Country of origin", "value": "New Zealand"}], [{"isTitle": true, "value": "Electric wiring systems (for power, lighting and heating circuits) in buildings"}, {"label": "View item details", "isLink": true, "value": "https://collection.motat.nz/objects/91311"}, {"isImage": true, "value": "https://collection.motat.nz/records/images/large/41611/183e869acc5e85eb966714ca4595c67b25dff9ea.jpg"}, {"label": "Year acquired", "value": "1949-01-01Z"}, {"label": "Country of origin", "value": "New Zealand"}], [{"isTitle": true, "value": "The troopers' tale the history of the Otago Mounted Rifles"}, {"label": "View item details", "isLink": true, "value": "https://collection.motat.nz/objects/91461"}, {"isImage": true, "value": "https://collection.motat.nz/records/images/large/41613/b7533a8b50d95a346f70e4a6d932fa36dfe16673.jpg"}, {"label": "Year acquired", "value": "2012-01-01Z"}, {"label": "Country of origin", "value": "New Zealand"}], [{"isTitle": true, "value": "Uniform Helmet [German, WWI]"}, {"label": "View item details", "isLink": true, "value": "https://collection.motat.nz/objects/9147"}, {"isImage": true, "value": "https://collection.motat.nz/records/images/large/41614/aa929d9e2e54b1673305f73795e3208803ffe0e8.jpg"}, {"label": "Year acquired", "value": "1914-01-01Z"}, {"label": "Country of origin", "value": "New Zealand"}]]