[[{"isTitle": true, "value": "Portable Potentiometer"}, {"label": "View item details", "isLink": true, "value": "https://collection.motat.nz/objects/91748"}, {"isImage": true, "value": "https://collection.motat.nz/records/images/large/42022/5fafd6bd01b9116c5bcaaad680bbb8b8352d8b1d.jpg"}, {"label": "Year acquired", "value": "1960-01-01Z"}, {"label": "Country of origin", "value": "New Zealand"}], [{"isTitle": true, "value": "Royal Air Force staff navigator course astronomical navigation"}, {"label": "View item details", "isLink": true, "value": "https://collection.motat.nz/objects/91770"}, {"isImage": true, "value": "https://collection.motat.nz/records/images/large/18268/9594651458dc26ae6454e2516c9c56f8129d2670.jpg"}, {"label": "Year acquired", "value": "1962-01-01Z"}, {"label": "Country of origin", "value": "New Zealand"}], [{"isTitle": true, "value": "Royal Air Force central navigation and control school"}, {"label": "View item details", "isLink": true, "value": "https://collection.motat.nz/objects/91771"}, {"isImage": true, "value": "https://collection.motat.nz/records/images/large/18268/9594651458dc26ae6454e2516c9c56f8129d2670.jpg"}, {"label": "Year acquired", "value": "1962-01-01Z"}, {"label": "Country of origin", "value": "New Zealand"}], [{"isTitle": true, "value": "[New Zealand Flying School Avro 504K]"}, {"label": "View item details", "isLink": true, "value": "https://collection.motat.nz/objects/91772"}, {"isImage": true, "value": "https://collection.motat.nz/records/images/large/42075/88286445073794106c3ba661c8ac14dcfa47a113.jpg"}, {"label": "Year acquired", "value": "1920-01-01Z"}, {"label": "Country of origin", "value": "New Zealand"}], [{"isTitle": true, "value": "[Walsh Brothers Avro 504K]"}, {"label": "View item details", "isLink": true, "value": "https://collection.motat.nz/objects/91773"}, {"isImage": true, "value": "https://collection.motat.nz/records/images/large/42076/b708ea2895bc84914a35d0365f7462813fbf6012.jpg"}, {"label": "Year acquired", "value": "1920-01-01Z"}, {"label": "Country of origin", "value": "New Zealand"}], [{"isTitle": true, "value": "[Avro 504K \"High Jinks\"]"}, {"label": "View item details", "isLink": true, "value": "https://collection.motat.nz/objects/91774"}, {"isImage": true, "value": "https://collection.motat.nz/records/images/large/42077/66222e69587b4f0b331960086d36bc95f1369026.jpg"}, {"label": "Year acquired", "value": "1920-01-01Z"}, {"label": "Country of origin", "value": "New Zealand"}], [{"isTitle": true, "value": "[Unidentified group portrait]"}, {"label": "View item details", "isLink": true, "value": "https://collection.motat.nz/objects/91775"}, {"isImage": true, "value": "https://collection.motat.nz/records/images/large/42078/ca144ca47638ff7e1244bcc3c3a314a4ebee8137.jpg"}, {"label": "Year acquired", "value": "1920-01-01Z"}, {"label": "Country of origin", "value": "New Zealand"}], [{"isTitle": true, "value": "[Crowds welcoming return of HMS Achilles]"}, {"label": "View item details", "isLink": true, "value": "https://collection.motat.nz/objects/91776"}, {"isImage": true, "value": "https://collection.motat.nz/records/images/large/42079/b6a00b9e1427430f86e090ee93c00ee1fb7f0c13.jpg"}, {"label": "Year acquired", "value": "1940-02-23Z"}, {"label": "Country of origin", "value": "New Zealand"}], [{"isTitle": true, "value": "[Bush scene]"}, {"label": "View item details", "isLink": true, "value": "https://collection.motat.nz/objects/91778"}, {"isImage": true, "value": "https://collection.motat.nz/records/images/large/42081/1eed0e12996d08e277441659d2fb2931d51b5399.jpg"}, {"label": "Year acquired", "value": "1920-01-01Z"}, {"label": "Country of origin", "value": "New Zealand"}], [{"isTitle": true, "value": "[Royal Tour 1920]"}, {"label": "View item details", "isLink": true, "value": "https://collection.motat.nz/objects/91782"}, {"isImage": true, "value": "https://collection.motat.nz/records/images/large/42085/ae7de5c67db9ad0fcb86935f9cfcac4d75f3a07e.jpg"}, {"label": "Year acquired", "value": "1920-05-05Z"}, {"label": "Country of origin", "value": "New Zealand"}]]