[[{"isTitle": true, "value": "NAC Stores Office"}, {"label": "View item details", "isLink": true, "value": "https://collection.motat.nz/objects/94385"}, {"isImage": true, "value": "https://collection.motat.nz/records/images/large/45561/1fb0acf0781f2ed8f76e2bdb83c175cb6f27e4cd.jpg"}, {"label": "Year acquired", "value": "1949-04-07Z"}, {"label": "Country of origin", "value": "New Zealand"}], [{"isTitle": true, "value": "NAC Car"}, {"label": "View item details", "isLink": true, "value": "https://collection.motat.nz/objects/94393"}, {"isImage": true, "value": "https://collection.motat.nz/records/images/large/45569/9826bf08c64fcef62a5724f1c448b51feb9d9cb8.jpg"}, {"label": "Year acquired", "value": "1947-02-01Z"}, {"label": "Country of origin", "value": "New Zealand"}], [{"isTitle": true, "value": "NAC Reservations Office"}, {"label": "View item details", "isLink": true, "value": "https://collection.motat.nz/objects/94407"}, {"isImage": true, "value": "https://collection.motat.nz/records/images/large/45583/0d4348f36e1de720c8033862673c98e1e1d87f9b.jpg"}, {"label": "Year acquired", "value": "1948-06-14Z"}, {"label": "Country of origin", "value": "New Zealand"}], [{"isTitle": true, "value": "Airport Cafetaria"}, {"label": "View item details", "isLink": true, "value": "https://collection.motat.nz/objects/94410"}, {"isImage": true, "value": "https://collection.motat.nz/records/images/large/45586/1b7b419a96d5c65474826564baa6647dd52f1fd3.jpg"}, {"label": "Year acquired", "value": "1956-08-30Z"}, {"label": "Country of origin", "value": "New Zealand"}], [{"isTitle": true, "value": "NAC Auckland Aircentre Opening  August 1982"}, {"label": "View item details", "isLink": true, "value": "https://collection.motat.nz/objects/94412"}, {"isImage": true, "value": "https://collection.motat.nz/records/images/large/45588/3aee3ef89739efd48cfb686b69825c7f03300dff.jpg"}, {"label": "Year acquired", "value": "1962-08-09Z"}, {"label": "Country of origin", "value": "New Zealand"}], [{"isTitle": true, "value": "NAC Auckland Aircentre Opening  August 1983"}, {"label": "View item details", "isLink": true, "value": "https://collection.motat.nz/objects/94413"}, {"isImage": true, "value": "https://collection.motat.nz/records/images/large/45589/40fe32acbea70faab2e0132f41f23a5c8860ea50.jpg"}, {"label": "Year acquired", "value": "1962-08-09Z"}, {"label": "Country of origin", "value": "New Zealand"}], [{"isTitle": true, "value": "NAC Auckland Aircentre Opening  August 1985"}, {"label": "View item details", "isLink": true, "value": "https://collection.motat.nz/objects/94415"}, {"isImage": true, "value": "https://collection.motat.nz/records/images/large/45591/720f8cef6a8a467f44475ec73dc457da30acf9cb.jpg"}, {"label": "Year acquired", "value": "1962-08-09Z"}, {"label": "Country of origin", "value": "New Zealand"}], [{"isTitle": true, "value": "NAC Auckland Aircentre Opening  August 1986"}, {"label": "View item details", "isLink": true, "value": "https://collection.motat.nz/objects/94416"}, {"isImage": true, "value": "https://collection.motat.nz/records/images/large/45592/beba8c0d5ba23fca30507f50cc704066079bf913.jpg"}, {"label": "Year acquired", "value": "1962-08-09Z"}, {"label": "Country of origin", "value": "New Zealand"}], [{"isTitle": true, "value": "NAC Auckland Aircentre Opening  August 1987"}, {"label": "View item details", "isLink": true, "value": "https://collection.motat.nz/objects/94417"}, {"isImage": true, "value": "https://collection.motat.nz/records/images/large/45593/c5f8150694b7fb0003cf11f45e03b10c24007100.jpg"}, {"label": "Year acquired", "value": "1962-08-09Z"}, {"label": "Country of origin", "value": "New Zealand"}], [{"isTitle": true, "value": "NAC Auckland Aircentre Opening  August 1988"}, {"label": "View item details", "isLink": true, "value": "https://collection.motat.nz/objects/94418"}, {"isImage": true, "value": "https://collection.motat.nz/records/images/large/45594/19713f096e809637bfc4205939c3ebdee3505690.jpg"}, {"label": "Year acquired", "value": "1962-08-09Z"}, {"label": "Country of origin", "value": "New Zealand"}]]